---
title: ç”¨javapçœ‹ä¸€ä¸‹finalæ˜¯ä»€ä¹ˆ
date: 2018-07-17 22:23:29
tags: [javap,java]
categories: java
---

> ä¸€ç›´å¾ˆå¥½å¥‡`final`çš„ç±»å­—æ®µåœ¨classæ–‡ä»¶æ˜¯æ€ä¹ˆè¡¨ç¤ºçš„ï¼Œæ‰€ä»¥ç”¨javapçœ‹çœ‹æ€ä¹ˆå›äº‹,ä¹Ÿé¡ºä¾¿å¤ä¹ ä¸‹å­—èŠ‚ç æŒ‡ä»¤ğŸ‘¿

# æ²¡æœ‰`final`ä¿®é¥°çš„ç±»çš„é™æ€å­—æ®µ

å®šä¹‰ä¸€ä¸ªç±»

```java
public class test{
  public static String str="ä¸¥";

  public static void main(String[] args){
        System.out.println(str);
  }
}

```

<!-- more -->

ç¼–è¯‘æŸ¥çœ‹classæ–‡ä»¶

````shell
javac test.java
javap -verbose test.class

//çœç•¥å¸¸é‡æ± 
{
  public static java.lang.String str;
    flags: ACC_PUBLIC, ACC_STATIC

  public test();
    flags: ACC_PUBLIC
    Code:
      stack=1, locals=1, args_size=1
         0: aload_0
         1: invokespecial #1                  // Method java/lang/Object."<init>":()V
         4: return
      LineNumberTable:
        line 1: 0

  public static void main(java.lang.String[]);
    flags: ACC_PUBLIC, ACC_STATIC
    Code:
      stack=2, locals=1, args_size=1
         0: getstatic     #2                  // Field java/lang/System.out:Ljava/io/PrintStream;
         3: getstatic     #3                  // Field str:Ljava/lang/String;
         6: invokevirtual #4                  // Method java/io/PrintStream.println:(Ljava/lang/String;)V
         9: return
      LineNumberTable:
        line 5: 0
        line 6: 9

  static {};
    flags: ACC_STATIC
    Code:
      stack=1, locals=0, args_size=0
         0: ldc           #5                  // String ä¸¥
         2: putstatic     #3                  // Field str:Ljava/lang/String;
         5: return
      LineNumberTable:
        line 2: 0
}

````

ä½ ä¼šå‘ç°`public static String str="ä¸¥";`ç›´æ¥ç¿»è¯‘æˆä¸€ä¸ªé™æ€å—

````
  static {};
    flags: ACC_STATIC
    Code:
      stack=1, locals=0, args_size=0
         0: ldc           #5                  // String ä¸¥
         2: putstatic     #3                  // Field str:Ljava/lang/String;
         5: return
      LineNumberTable:
        line 2: 0
````

ä¸Šé¢`ldc`çš„æŒ‡ä»¤å°±æ˜¯æŠŠå¸¸é‡ä»å¸¸é‡æ± è¯»åˆ°æ“ä½œæ•°æ ˆï¼Œ`putstatic`æŒ‡ä»¤ä»æ ˆé¡¶èµ‹å€¼ç»™ç±»çš„é™æ€å­—æ®µ`str`,è¿™ä¸ªå­—æ®µä¹‹ååœ¨`main`å‡½æ•°ä¼šè¯»å‡ºæ¥ã€‚

````
  public static void main(java.lang.String[]);
    flags: ACC_PUBLIC, ACC_STATIC
    Code:
      stack=2, locals=1, args_size=1
         0: getstatic     #2                  // Field java/lang/System.out:Ljava/io/PrintStream;
         3: getstatic     #3                  // Field str:Ljava/lang/String;
         6: invokevirtual #4                  // Method java/io/PrintStream.println:(Ljava/lang/String;)V
         9: return
      LineNumberTable:
        line 5: 0
        line 6: 9
````
`getstatic`æ˜¯ç”¨æ¥è¯»å–ç±»çš„é™æ€å­—æ®µçš„ï¼Œè¿™é‡Œè¯»å‡ºæ¥æ”¾å…¥æ“ä½œæ•°æ ˆã€‚

# æœ‰`final`ä¿®é¥°çš„ç±»é™æ€å­—æ®µ

æ”¹ä¸€ä¸‹è¿™ä¸ªç±»ï¼ŒåŠ `final`ä¿®é¥°ä¸‹

```java
public class test{
  public static final String str="ä¸¥";

  public static void main(String[] args){
        System.out.println(str);
  }
}

```

ç¼–è¯‘æŸ¥çœ‹classæ–‡ä»¶

````shell
javac test.java
javap -verbose test.class

# çœç•¥å¸¸é‡æ± 
{
  public static final java.lang.String str;
    flags: ACC_PUBLIC, ACC_STATIC, ACC_FINAL
    ConstantValue: String ä¸¥

  public test();
    flags: ACC_PUBLIC
    Code:
      stack=1, locals=1, args_size=1
         0: aload_0
         1: invokespecial #1                  // Method java/lang/Object."<init>":()V
         4: return
      LineNumberTable:
        line 1: 0

  public static void main(java.lang.String[]);
    flags: ACC_PUBLIC, ACC_STATIC
    Code:
      stack=2, locals=1, args_size=1
         0: getstatic     #2                  // Field java/lang/System.out:Ljava/io/PrintStream;
         3: ldc           #3                  // String ä¸¥
         5: invokevirtual #4                  // Method java/io/PrintStream.println:(Ljava/lang/String;)V
         8: return
      LineNumberTable:
        line 5: 0
        line 6: 8
}
````
ä½ ä¼šå‘ç°classæ–‡ä»¶æ²¡æœ‰ä¹‹å‰çš„é™æ€å—äº†ï¼Œè€Œä¸”ä¹Ÿä¸å†ç”¨`getstatic`æŒ‡ä»¤è·å–å­—æ®µçš„å€¼ï¼Œè€Œæ˜¯ç›´æ¥`ldc`æŒ‡ä»¤å–å¸¸é‡æ± çš„å€¼ã€‚

æ¥ä¸‹æ¥çœ‹çœ‹å®ä¾‹å­—æ®µåœ¨åŠ `final`æˆ–ä¸åŠ ä¼šä¸ä¼šæœ‰ä»€ä¹ˆä¸åŒå‘¢

# ä¸åŠ finalçš„å®ä¾‹å­—æ®µ

````java
public class test{
  public  String str="ä¸¥";

  public static void main(String[] args){
        test t=new test();
        System.out.println(t.str);
  }
}

````

ç±»æ–‡ä»¶

````
//çœç•¥æ²¡ç”¨çš„äº†ã€‚ã€‚ã€‚
{
  public java.lang.String str;
    flags: ACC_PUBLIC

  public test();
    flags: ACC_PUBLIC
    Code:
      stack=2, locals=1, args_size=1
         0: aload_0
         1: invokespecial #1                  // Method java/lang/Object."<init>":()V
         4: aload_0
         5: ldc           #2                  // String ä¸¥
         7: putfield      #3                  // Field str:Ljava/lang/String;
        10: return
      LineNumberTable:
        line 1: 0
        line 2: 4

  public static void main(java.lang.String[]);
    flags: ACC_PUBLIC, ACC_STATIC
    Code:
      stack=2, locals=2, args_size=1
         0: new           #4                  // class test
         3: dup
         4: invokespecial #5                  // Method "<init>":()V
         7: astore_1
         8: getstatic     #6                  // Field java/lang/System.out:Ljava/io/PrintStream;
        11: aload_1
        12: getfield      #3                  // Field str:Ljava/lang/String;
        15: invokevirtual #7                  // Method java/io/PrintStream.println:(Ljava/lang/String;)V
        18: return
      LineNumberTable:
        line 5: 0
        line 6: 8
        line 7: 18
}

````
æ„é€ å‡½æ•°é‡Œé¢ç”¨`ldc`åˆå§‹åŒ–äº†å®ä¾‹å­—æ®µ`str`çš„å€¼,ç„¶ååœ¨mainå‡½æ•°é‡Œé¢ç”¨`getfield`æŒ‡ä»¤ï¼Œè·å–`t`å®ä¾‹çš„`str`çš„å€¼ã€‚

# åŠ `final`çš„å®ä¾‹å­—æ®µ

````java
public class test{
  public final String str="ä¸¥";

  public static void main(String[] args){
        test t=new test();
        System.out.println(t.str);
  }
}

````

ç±»æ–‡ä»¶

````
//çœç•¥æ²¡ç”¨çš„äº†ã€‚ã€‚ã€‚
{
  public final java.lang.String str;
    flags: ACC_PUBLIC, ACC_FINAL
    ConstantValue: String ä¸¥

  public test();
    flags: ACC_PUBLIC
    Code:
      stack=2, locals=1, args_size=1
         0: aload_0
         1: invokespecial #1                  // Method java/lang/Object."<init>":()V
         4: aload_0
         5: ldc           #2                  // String ä¸¥
         7: putfield      #3                  // Field str:Ljava/lang/String;
        10: return
      LineNumberTable:
        line 1: 0
        line 2: 4

  public static void main(java.lang.String[]);
    flags: ACC_PUBLIC, ACC_STATIC
    Code:
      stack=2, locals=2, args_size=1
         0: new           #4                  // class test
         3: dup
         4: invokespecial #5                  // Method "<init>":()V
         7: astore_1
         8: getstatic     #6                  // Field java/lang/System.out:Ljava/io/PrintStream;
        11: aload_1
        12: invokevirtual #7                  // Method java/lang/Object.getClass:()Ljava/lang/Class;
        15: pop
        16: ldc           #2                  // String ä¸¥
        18: invokevirtual #8                  // Method java/io/PrintStream.println:(Ljava/lang/String;)V
        21: return
      LineNumberTable:
        line 5: 0
        line 6: 8
        line 7: 21
}

````
`getfield`æŒ‡ä»¤å˜æˆäº†ç†Ÿæ‚‰çš„`ldc`,å¾ˆæ˜æ˜¾äº†ï¼ŒåŠ äº†`final`ä¹‹åå°±å»å¸¸é‡æ± å»æ‰¾ï¼Œå°±ä¸éœ€è¦ç”¨`getfield`æŒ‡ä»¤ã€‚

ä¸Šé¢çš„å­—æ®µæ˜¯å­—ç¬¦ä¸²ï¼Œé‚£æ¥ä¸‹æ¥çœ‹çœ‹æ•°å­—çš„å­—æ®µä¼šæ€ä¹ˆæ ·å‘¢

# æ•°å­—çš„é`final`é™æ€å­—æ®µ

ä¸Šä»£ç 

````java
public class test{
  public static int i=100;

  public static void main(String[] args){
        System.out.println(i);
  }
}
````

javapç»“æœ

````
//çœç•¥å¸¸é‡æ± 
{
  public static int i;
    flags: ACC_PUBLIC, ACC_STATIC

  public test();
    flags: ACC_PUBLIC
    Code:
      stack=1, locals=1, args_size=1
         0: aload_0
         1: invokespecial #1                  // Method java/lang/Object."<init>":()V
         4: return
      LineNumberTable:
        line 1: 0

  public static void main(java.lang.String[]);
    flags: ACC_PUBLIC, ACC_STATIC
    Code:
      stack=2, locals=1, args_size=1
         0: getstatic     #2                  // Field java/lang/System.out:Ljava/io/PrintStream;
         3: getstatic     #3                  // Field i:I
         6: invokevirtual #4                  // Method java/io/PrintStream.println:(I)V
         9: return
      LineNumberTable:
        line 6: 0
        line 7: 9

  static {};
    flags: ACC_STATIC
    Code:
      stack=1, locals=0, args_size=0
         0: bipush        100
         2: putstatic     #3                  // Field i:I
         5: return
      LineNumberTable:
        line 3: 0
}

````

åŸºæœ¬å·®ä¸å¤šï¼Œåªæ˜¯`ldc`æ¢æˆäº†`bipush`ã€‚`bipush`å°±æ˜¯æŠŠåé¢çš„æ“ä½œæ•°ï¼ˆ100ï¼‰å‹å…¥æ ˆã€‚å¦‚æœå‹å…¥çš„ä¸æ˜¯100ï¼Œè€Œæ˜¯æ›´å¤§æˆ–æ›´å°ï¼Œé‚£ä¹ˆç”¨çš„æŒ‡ä»¤å°±ä¼šä¸åŒçš„äº†ï¼Œä¾‹å¦‚`iconst_1`æŒ‡ä»¤ï¼Œå°±æ˜¯å‹å…¥1åˆ°æ ˆã€‚è‡³äºmainå‡½æ•°é‡Œé¢ï¼Œè¿˜æ˜¯ç”¨`getstatic`æŒ‡ä»¤è·å–å­—æ®µçš„å€¼ã€‚

# æ•°å­—çš„`final`é™æ€å­—æ®µ

ä¸Šä»£ç 

````java
public class test{
  public static final int i=100;

  public static void main(String[] args){
        System.out.println(i);
  }
}
````

javapç»“æœ

````

{
  public static final int i;
    flags: ACC_PUBLIC, ACC_STATIC, ACC_FINAL
    ConstantValue: int 100

  public test();
    flags: ACC_PUBLIC
    Code:
      stack=1, locals=1, args_size=1
         0: aload_0
         1: invokespecial #1                  // Method java/lang/Object."<init>":()V
         4: return
      LineNumberTable:
        line 1: 0

  public static void main(java.lang.String[]);
    flags: ACC_PUBLIC, ACC_STATIC
    Code:
      stack=2, locals=1, args_size=1
         0: getstatic     #2                  // Field java/lang/System.out:Ljava/io/PrintStream;
         3: bipush        100
         5: invokevirtual #3                  // Method java/io/PrintStream.println:(I)V
         8: return
      LineNumberTable:
        line 6: 0
        line 7: 8
}

````
æ²¡å•¥æƒŠå–œçš„ï¼Œå°±æ˜¯é™æ€å—å»æ‰ï¼Œéœ€è¦è·å–å­—æ®µçš„å€¼çš„åœ°æ–¹ä»`getstatic`å˜æˆäº†`bipush`ã€‚

è‡³äºå®ä¾‹å­—æ®µæ˜¯æ€ä¹ˆæ ·çš„ï¼Œåº”è¯¥éƒ½å·®ä¸å¤šäº†ï¼Œå°±ä¸åˆ—ä¸¾äº†ï¼Œæ¥ä¸‹æ¥çœ‹çœ‹å­—æ®µç±»å‹æ˜¯å¼•ç”¨çš„æ˜¯æ€ä¹ˆæ ·å‘¢ã€‚

# åŠ `final`çš„å¼•ç”¨ç±»å‹å­—æ®µ

ä¸Šä»£ç 

````java
public class test{
  public static final Object o=new Object();

  public static void main(String[] args){
        System.out.println(o);
  }
}
````

javapç»“æœ

````

{
  public static final java.lang.Object o;
    flags: ACC_PUBLIC, ACC_STATIC, ACC_FINAL

  public test();
    flags: ACC_PUBLIC
    Code:
      stack=1, locals=1, args_size=1
         0: aload_0
         1: invokespecial #1                  // Method java/lang/Object."<init>":()V
         4: return
      LineNumberTable:
        line 1: 0

  public static void main(java.lang.String[]);
    flags: ACC_PUBLIC, ACC_STATIC
    Code:
      stack=2, locals=1, args_size=1
         0: getstatic     #2                  // Field java/lang/System.out:Ljava/io/PrintStream;
         3: getstatic     #3                  // Field o:Ljava/lang/Object;
         6: invokevirtual #4                  // Method java/io/PrintStream.println:(Ljava/lang/Object;)V
         9: return
      LineNumberTable:
        line 6: 0
        line 7: 9

  static {};
    flags: ACC_STATIC
    Code:
      stack=2, locals=0, args_size=0
         0: new           #5                  // class java/lang/Object
         3: dup
         4: invokespecial #1                  // Method java/lang/Object."<init>":()V
         7: putstatic     #3                  // Field o:Ljava/lang/Object;
        10: return
      LineNumberTable:
        line 3: 0
}

````

è¿™é‡Œç›´æ¥ä¸Š`final`çš„ç‰ˆæœ¬ï¼Œæ˜¯å› ä¸ºåŠ ä¸åŠ `final`ï¼Œå…¶å®éƒ½æ˜¯ä¸€æ ·çš„ï¼Œéƒ½æ˜¯æœ‰é™æ€å—ï¼Œå¼•ç”¨çš„æ—¶å€™ä¸å†æœ‰ä»€ä¹ˆå…¶ä»–æŒ‡ä»¤äº†ï¼Œè€è€å®å®çš„ç”¨`getstatic`ã€‚


# æ€»ç»“

å¯¹äºå­—ç¬¦ä¸²æˆ–è€…æ•°å­—ç±»å‹ï¼Œä»–ä»¬éƒ½æ˜¯å±äºå­—é¢é‡ï¼Œç¼–è¯‘æ—¶å·²ç»çŸ¥é“ï¼Œä»–ä»¬è¦ä¹ˆå­˜åœ¨å¸¸é‡æ± é‡Œé¢ï¼Œè¦ä¹ˆå­˜åœ¨æŒ‡ä»¤çš„æ“ä½œæ•°é‡Œé¢ï¼Œæ‰€ä»¥åŠ `final`æ ‡è¯†çš„æƒ…å†µä¸‹ï¼Œè·å–å€¼æ—¶ä¸ç”¨å†åˆ°å…³è”çš„å¯¹è±¡åº•ä¸‹å»è·å–äº†ï¼Œå› ä¸º`final`å°±æ˜¯ä¸å˜ï¼Œç›´æ¥è°ƒç”¨ç›¸å…³æŒ‡ä»¤å»å¸¸é‡æ± ï¼Œæˆ–è€…ç›´æ¥æ“ä½œæ•°å–å°±å¥½ã€‚

å¯¹äºå¼•ç”¨ç±»å‹ï¼Œè¿™ä¸ªåŸºæœ¬è¦åˆ°è¿è¡Œæ—¶æ‰èƒ½ç¡®è®¤ä»–ä»¬çš„å¼•ç”¨åœ°å€ï¼Œæ‰€ä»¥åŠ ä¸åŠ `final`éƒ½æ˜¯ä¸€æ ·ã€‚

çœ‹æ¥å­—èŠ‚ç æ‰æ˜¯æœ€èƒ½ç¡®å®šjavaæ˜¯æ€ä¹ˆè¿è¡Œçš„ï¼Œæ‰€ä»¥ä¸å…¶æ‰¾ç½‘ä¸Šçš„è¯´æ³•ä¸å¦‚`javap`ä¸€ä¸‹çœ‹çœ‹ã€‚



